awesome_ryver/__init__.py
awesome_ryver/__main__.py
awesome_ryver/__version__.py
awesome_ryver/main.py
awesome_ryver-0.1.3.dist-info/LICENSE
awesome_ryver-0.1.3.dist-info/METADATA
awesome_ryver-0.1.3.dist-info/WHEEL
awesome_ryver-0.1.3.dist-info/entry_points.txt
awesome_ryver-0.1.3.dist-info/top_level.txt
awesome_ryver-0.1.3.dist-info/zip-safe
awesome_ryver-0.1.3.dist-info/RECORD
