Metadata-Version: 2.1
Name: awesome-ryver
Version: 0.1.3
Summary: Client-side plugin adding extra features to Ryver
Home-page: https://github.com/Nauja/awesome-ryver
Author: Nauja
Author-email: jeremymorosi@hotmail.com
License: UNKNOWN
Project-URL: Bug Tracker, https://github.com/Nauja/awesome-ryver/issues
Project-URL: Source Code, https://github.com/Nauja/awesome-ryver/
Platform: UNKNOWN
Classifier: Programming Language :: Python :: 3.9
Requires-Python: >=3.9
License-File: LICENSE
Requires-Dist: requests
Requires-Dist: websocket
Requires-Dist: argparse
